altamus_pymavlink/CSVReader.py
altamus_pymavlink/DFReader.py
altamus_pymavlink/__init__.py
altamus_pymavlink/fgFDM.py
altamus_pymavlink/mavexpression.py
altamus_pymavlink/mavextra.py
altamus_pymavlink/mavftp.py
altamus_pymavlink/mavftp_op.py
altamus_pymavlink/mavftpfs.py
altamus_pymavlink/mavparm.py
altamus_pymavlink/mavtestgen.py
altamus_pymavlink/mavutil.py
altamus_pymavlink/mavwp.py
altamus_pymavlink/quaternion.py
altamus_pymavlink/rotmat.py
altamus_pymavlink/setup.py
altamus_pymavlink/dialects/__init__.py
altamus_pymavlink/dialects/v10/__init__.py
altamus_pymavlink/dialects/v10/all.xml
altamus_pymavlink/dialects/v10/altamus.py
altamus_pymavlink/dialects/v10/altamus.xml
altamus_pymavlink/dialects/v10/altamus_legacy.py
altamus_pymavlink/dialects/v10/altamus_legacy.xml
altamus_pymavlink/dialects/v10/ardupilotmega.py
altamus_pymavlink/dialects/v10/ardupilotmega.xml
altamus_pymavlink/dialects/v10/common.py
altamus_pymavlink/dialects/v10/common.xml
altamus_pymavlink/dialects/v10/common_minimal.py
altamus_pymavlink/dialects/v10/common_minimal.xml
altamus_pymavlink/dialects/v10/minimal.py
altamus_pymavlink/dialects/v10/minimal.xml
altamus_pymavlink/dialects/v10/python_array_test.py
altamus_pymavlink/dialects/v10/python_array_test.xml
altamus_pymavlink/dialects/v10/standard.py
altamus_pymavlink/dialects/v10/standard.xml
altamus_pymavlink/dialects/v10/test.py
altamus_pymavlink/dialects/v10/test.xml
altamus_pymavlink/dialects/v10/python2/__init__.py
altamus_pymavlink/dialects/v10/python2/altamus.py
altamus_pymavlink/dialects/v10/python2/altamus_legacy.py
altamus_pymavlink/dialects/v10/python2/ardupilotmega.py
altamus_pymavlink/dialects/v10/python2/common.py
altamus_pymavlink/dialects/v10/python2/common_minimal.py
altamus_pymavlink/dialects/v10/python2/minimal.py
altamus_pymavlink/dialects/v10/python2/python_array_test.py
altamus_pymavlink/dialects/v10/python2/standard.py
altamus_pymavlink/dialects/v10/python2/test.py
altamus_pymavlink/dialects/v20/__init__.py
altamus_pymavlink-1.1.7.dist-info/licenses/COPYING
altamus_pymavlink-1.1.7.dist-info/METADATA
altamus_pymavlink-1.1.7.dist-info/WHEEL
altamus_pymavlink-1.1.7.dist-info/top_level.txt
altamus_pymavlink-1.1.7.dist-info/RECORD
